{
  "kind": "collectionType",
  "collectionName": "ateliers",
  "info": {
    "name": "ateliers",
    "description": ""
  },
  "options": {
    "increments": true,
    "timestamps": true,
    "draftAndPublish": false
  },
  "attributes": {
    "titre": {
      "type": "string"
    },
    "date": {
      "type": "date"
    },
    "debut": {
      "type": "time"
    },
    "fin": {
      "type": "time"
    },
    "nbParticipants": {
      "type": "integer"
    },
    "lesTarifs": {
      "type": "component",
      "repeatable": true,
      "component": "ateliers.tarif"
    },
    "espace": {
      "model": "espaces",
      "via": "ateliers"
    },
    "lieu": {
      "type": "string"
    },
    "description": {
      "type": "richtext"
    },
    "inscriptions_ateliers": {
      "collection": "inscriptions-ateliers",
      "via": "atelier"
    },
    "surInscription": {
      "type": "boolean",
      "default": true
    },
    "urlImage": {
      "type": "string"
    },
    "encadrant": {
      "type": "email"
    }
  }
}
